dsplayer_spotify/__init__.py
dsplayer_spotify/spotify.py
plugin/__init__.py
plugin/plugin.py
dsplayer_spotify-1.3.0.dist-info/LICENSE
dsplayer_spotify-1.3.0.dist-info/METADATA
dsplayer_spotify-1.3.0.dist-info/WHEEL
dsplayer_spotify-1.3.0.dist-info/entry_points.txt
dsplayer_spotify-1.3.0.dist-info/top_level.txt
dsplayer_spotify-1.3.0.dist-info/RECORD
