Metadata-Version: 2.1
Name: dsplayer-spotify
Version: 1.3.0
License-File: LICENSE
Requires-Dist: dsplayer
Requires-Dist: yt-dlp
Requires-Dist: spotipy
